MANIFEST.in
README.rst
bootstrap.py
buildout.cfg
setup.py
collective/__init__.py
collective.portlet.actions.egg-info/PKG-INFO
collective.portlet.actions.egg-info/SOURCES.txt
collective.portlet.actions.egg-info/dependency_links.txt
collective.portlet.actions.egg-info/entry_points.txt
collective.portlet.actions.egg-info/namespace_packages.txt
collective.portlet.actions.egg-info/not-zip-safe
collective.portlet.actions.egg-info/requires.txt
collective.portlet.actions.egg-info/top_level.txt
collective/portlet/__init__.py
collective/portlet/actions/__init__.py
collective/portlet/actions/actionsportlet.css
collective/portlet/actions/actionsportlet.pt
collective/portlet/actions/actionsportlet.py
collective/portlet/actions/configure.zcml
collective/portlet/actions/locales/README.txt
collective/portlet/actions/locales/collective.portlet.actions-manual.pot
collective/portlet/actions/locales/collective.portlet.actions.pot
collective/portlet/actions/locales/updatelocales.py
collective/portlet/actions/locales/fr/LC_MESSAGES/collective.portlet.actions.po
collective/portlet/actions/locales/it/LC_MESSAGES/collective.portlet.actions.po
collective/portlet/actions/profiles/default/cssregistry.xml
collective/portlet/actions/profiles/default/metadata.xml
collective/portlet/actions/profiles/default/portlets.xml
collective/portlet/actions/tests/__init__.py
collective/portlet/actions/tests/base.py
collective/portlet/actions/tests/test_portlet.py
docs/HISTORY.txt
docs/INSTALL.txt
docs/LICENSE.GPL
docs/LICENSE.txt
docs/TODO.txt