Metadata-Version: 1.1
Name: collective.portlet.actions
Version: 1.2.3
Summary: A portlet that provides the links of an action category
Home-page: http://plone.org/products/collective-portlet-actions
Author: Gilles Lenfant
Author-email: gilles.lenfant@alterway.fr
License: GPL
Keywords: plone portlet
Platform: UNKNOWN
Classifier: Framework :: Plone :: 3.2
Classifier: Framework :: Plone :: 3.3
Classifier: Framework :: Plone :: 4.0
Classifier: Framework :: Plone :: 4.1
Classifier: Framework :: Plone :: 4.2
Classifier: Programming Language :: Python
Classifier: Programming Language :: Python :: 2.6
Classifier: Programming Language :: Python :: 2.7
Classifier: Topic :: Software Development :: Libraries :: Python Modules
